Metadata-Version: 1.1
Name: lazyhttp
Version: 0.0.3
Summary: Makes it quick to make HTTP servers
Home-page: https://github.com/pdxjohnny/lazyhttp
Author: John Andersen
Author-email: johnandersenpdx@gmail.com
License: MIT
Download-URL: https://github.com/pdxjohnny/lazyhttp/tarball/0.0.3
Keywords: http,server,development
Platform: UNKNOWN
Classifier: Environment :: Console
Classifier: Operating System :: POSIX :: Linux
Classifier: License :: OSI Approved :: MIT License
Classifier: Programming Language :: Python :: 3.5
Classifier: Intended Audience :: Developers
